{
    "family": "rt6xx",
    "inputImageFile": "./workspace/input_images/testfffffff.bin",
    "imageLinkAddress": "0x0",
    "outputImageExecutionTarget": "RAM",
    "outputImageAuthenticationType": "Encrypted + Signed",
    "deviceKeySource": "Key Store",
    "outputImageEncryptionKeyFile": "./workspace/keys/userkey.txt",
    "enableTrustZone": true,
    "trustZonePresetFile": "./workspace/trust_zone_config/example_rt6xxA0.json",
    "useKeyStore": true,
    "keyStoreFile": "./workspace/key_store/key_store_rt6xx.bin",
    "rootCertificate0File": "./workspace/keys_and_certs/selfsign_v3.der.crt",
    "rootCertificate1File": "./workspace/keys_and_certs/selfsign_v3.der.crt",
    "rootCertificate2File": "",
    "rootCertificate3File": "",
    "mainCertChainId": 1,
    "mainCertPrivateKeyFile": "./workspace/keys_and_certs/selfsign_privatekey_rsa2048.pem",
    "masterBootOutputFile": "./workspace/output_images/test_output.bin"
}